mozart_api/__init__.py
mozart_api/api/__init__.py
mozart_api/api/beolink_api.py
mozart_api/api/bluetooth_api.py
mozart_api/api/content_api.py
mozart_api/api/deezer_api.py
mozart_api/api/mozart_api.py
mozart_api/api/overlay_api.py
mozart_api/api/playback_api.py
mozart_api/api/power_api.py
mozart_api/api/product_api.py
mozart_api/api/remote_api.py
mozart_api/api/scenes_api.py
mozart_api/api/settings_api.py
mozart_api/api/software_update_api.py
mozart_api/api/sound_api.py
mozart_api/api/speaker_group_api.py
mozart_api/api/stand_api.py
mozart_api/api_client.py
mozart_api/api_response.py
mozart_api/configuration.py
mozart_api/exceptions.py
mozart_api/models/__init__.py
mozart_api/models/action.py
mozart_api/models/alarm_timer_event_data.py
mozart_api/models/alarm_triggered_info.py
mozart_api/models/ambience.py
mozart_api/models/ambience_feature.py
mozart_api/models/ambience_range.py
mozart_api/models/art.py
mozart_api/models/balance.py
mozart_api/models/balance_feature.py
mozart_api/models/balance_range.py
mozart_api/models/bass.py
mozart_api/models/bass_feature.py
mozart_api/models/bass_management.py
mozart_api/models/bass_management_feature.py
mozart_api/models/bass_management_range.py
mozart_api/models/bass_range.py
mozart_api/models/battery_state.py
mozart_api/models/beo_remote_button.py
mozart_api/models/beolink_available_listener.py
mozart_api/models/beolink_experience.py
mozart_api/models/beolink_experiences_result.py
mozart_api/models/beolink_join_request.py
mozart_api/models/beolink_join_result.py
mozart_api/models/beolink_leader.py
mozart_api/models/beolink_listener.py
mozart_api/models/beolink_peer.py
mozart_api/models/bluetooth_device.py
mozart_api/models/bluetooth_device_list.py
mozart_api/models/button_event.py
mozart_api/models/compression.py
mozart_api/models/compression_feature.py
mozart_api/models/compression_range.py
mozart_api/models/content_item.py
mozart_api/models/directivity.py
mozart_api/models/directivity_feature.py
mozart_api-3.4.1.8.7.dist-info/LICENSE
mozart_api-3.4.1.8.7.dist-info/METADATA
mozart_api-3.4.1.8.7.dist-info/WHEEL
mozart_api-3.4.1.8.7.dist-info/entry_points.txt
mozart_api-3.4.1.8.7.dist-info/RECORD
